protes/__init__.py
protes/animation.py
protes/protes.py
protes/protes_general.py
protes-0.3.12.dist-info/METADATA
protes-0.3.12.dist-info/WHEEL
protes-0.3.12.dist-info/top_level.txt
protes-0.3.12.dist-info/RECORD
